visualist/__init__.py
visualist/fonts/Roboto-Medium.ttf
visualist-0.3.0.dist-info/LICENSE
visualist-0.3.0.dist-info/METADATA
visualist-0.3.0.dist-info/WHEEL
visualist-0.3.0.dist-info/top_level.txt
visualist-0.3.0.dist-info/RECORD
