Metadata-Version: 2.1
Name: visualist
Version: 0.3.0
Summary: A simple library to visualize lists.
Home-page: https://github.com/ThiNepo/visualist
Author: Thiago Nepomuceno
Author-email: thi.nepo@gmail.com
Classifier: Programming Language :: Python :: 3
Classifier: License :: OSI Approved :: GNU General Public License v3 or later (GPLv3+)
Classifier: Operating System :: OS Independent
License-File: LICENSE
Requires-Dist: Pillow >=10.0.0
